LICENSE
MANIFEST.in
README.md
setup.cfg
setup.py
parallel_pro/__init__.py
parallel_pro.egg-info/PKG-INFO
parallel_pro.egg-info/SOURCES.txt
parallel_pro.egg-info/dependency_links.txt
parallel_pro.egg-info/requires.txt
parallel_pro.egg-info/top_level.txt