Metadata-Version: 2.1
Name: parallel-pro
Version: 0.0.1
Summary: parallel_pro is a simple package for parallel processing
Home-page: https://github.com/scionoftech/parallel_pro
Author: Sai Kumar Yava
License: MIT
Keywords: parallel,multi processing
Platform: UNKNOWN
Classifier: Development Status :: 5 - Production/Stable
Classifier: Programming Language :: Python
Classifier: Programming Language :: Python :: 3.6
Classifier: Programming Language :: Python :: 3.7
Classifier: Programming Language :: Python :: 3.8
Classifier: License :: OSI Approved :: MIT License
